setup.py
calc/__init__.py
moh0009_calc.egg-info/PKG-INFO
moh0009_calc.egg-info/SOURCES.txt
moh0009_calc.egg-info/dependency_links.txt
moh0009_calc.egg-info/top_level.txt